dotprompt_handlebars-0.1.1.dist-info/METADATA
dotprompt_handlebars-0.1.1.dist-info/WHEEL
dotprompt_handlebars-0.1.1.dist-info/licenses/LICENSE
handlebarrz/_native.pyi
handlebarrz/py.typed
handlebarrz/__init__.py
handlebarrz/_native.cpython-312-aarch64-linux-gnu.so
dotprompt_handlebars-0.1.1.dist-info/RECORD
