Metadata-Version: 2.4
Name: dotprompt_handlebars
Version: 0.1.1
Classifier: Development Status :: 3 - Alpha
Classifier: Programming Language :: Python :: 3
Classifier: Programming Language :: Python :: 3.10
Classifier: Programming Language :: Python :: 3.11
Classifier: Programming Language :: Python :: 3.12
Classifier: Programming Language :: Python :: 3.13
Classifier: Programming Language :: Rust
Classifier: Topic :: Text Processing :: Markup
Classifier: License :: OSI Approved :: Apache Software License
Requires-Dist: strenum>=0.4.15 ; python_full_version < '3.11'
Requires-Dist: structlog>=25.2.0
License-File: LICENSE
Summary: Handlebars library for Python based on handlebars-rust.
Home-Page: https://github.com/google/dotprompt
Author: Yesudeep Mangalapilly <yesudeep@google.com>
Author-email: Yesudeep Mangalapilly <yesudeep@google.com>
License: Apache-2.0
Requires-Python: >=3.10
Project-URL: Source Code, https://github.com/google/dotprompt
